{"version": 0.6, "generator": "Overpass API 0.7.62.1 084b4234", "osm3s": {"timestamp_osm_base": "2024-07-25T19:04:04Z", "copyright": "The data included in this document is from www.openstreetmap.org. The data is made available under ODbL."}, "elements": [{"type": "node", "id": 7216846351, "lat": 40.787338, "lon": -82.5899041, "tags": {"bench": "yes", "bus": "yes", "highway": "bus_stop", "operator": "RCT", "public_transport": "platform", "shelter": "no", "source": "mapillary"}}, {"type": "node", "id": 7216846353, "lat": 40.7895601, "lon": -82.5927144, "tags": {"bench": "yes", "bus": "yes", "highway": "bus_stop", "operator": "RCT", "public_transport": "platform", "shelter": "no", "source": "mapillary"}}]}