[{"place_id": 317349083, "licence": "Data \u00a9 OpenStreetMap contributors, ODbL 1.0. http://osm.org/copyright", "osm_type": "node", "osm_id": 1758055806, "lat": "39.5488543", "lon": "-105.001504", "class": "amenity", "type": "fast_food", "place_rank": 30, "importance": 9.99999999995449e-06, "addresstype": "amenity", "name": "Which Wich?", "display_name": "Which Wich?, 1100, Sergeant Jon Stiles Drive, Town Center, Douglas County, Colorado, 80129, United States", "boundingbox": ["39.5488043", "39.5489043", "-105.0015540", "-105.0014540"]}]