{"version": 0.6, "generator": "Overpass API 0.7.62.1 084b4234", "osm3s": {"timestamp_osm_base": "2024-07-25T14:56:30Z", "copyright": "The data included in this document is from www.openstreetmap.org. The data is made available under ODbL."}, "elements": [{"type": "node", "id": 198967387, "lat": 40.3754171, "lon": -82.8292099, "tags": {"highway": "traffic_signals", "traffic_signals": "signal"}}, {"type": "node", "id": 198967658, "lat": 40.354448, "lon": -82.831237}, {"type": "node", "id": 198967931, "lat": 40.356766, "lon": -82.831006}, {"type": "node", "id": 198970761, "lat": 40.3728072, "lon": -82.8294098, "tags": {"highway": "traffic_signals", "traffic_signals": "signal"}}, {"type": "node", "id": 198976020, "lat": 40.355001, "lon": -82.83118}, {"type": "node", "id": 198976022, "lat": 40.358242, "lon": -82.830866}, {"type": "node", "id": 198976023, "lat": 40.361341, "lon": -82.830558}, {"type": "node", "id": 198976027, "lat": 40.366443, "lon": -82.8300965}, {"type": "node", "id": 198976030, "lat": 40.3673501, "lon": -82.8299922}, {"type": "node", "id": 198976032, "lat": 40.3683408, "lon": -82.8298721}, {"type": "node", "id": 198976035, "lat": 40.3717285, "lon": -82.8294984}, {"type": "node", "id": 198976043, "lat": 40.3748718, "lon": -82.8292585}, {"type": "node", "id": 198976050, "lat": 40.3768074, "lon": -82.8290814}, {"type": "node", "id": 198976061, "lat": 40.3798905, "lon": -82.8288033}, {"type": "node", "id": 198976066, "lat": 40.3804844, "lon": -82.8287261}, {"type": "node", "id": 198977862, "lat": 40.372639, "lon": -82.854073}, {"type": "node", "id": 198991050, "lat": 40.3717231, "lon": -82.82932, "tags": {"highway": "stop"}}, {"type": "node", "id": 198991052, "lat": 40.3717233, "lon": -82.828991}, {"type": "node", "id": 198991054, "lat": 40.3717399, "lon": -82.8288241}, {"type": "node", "id": 198991056, "lat": 40.3718725, "lon": -82.828115}, {"type": "node", "id": 198991063, "lat": 40.3719182, "lon": -82.827977}, {"type": "node", "id": 198991065, "lat": 40.3724065, "lon": -82.8269623}, {"type": "node", "id": 198991069, "lat": 40.3724817, "lon": -82.8267663}, {"type": "node", "id": 198991072, "lat": 40.3725299, "lon": -82.8265977}, {"type": "node", "id": 198991074, "lat": 40.3725521, "lon": -82.8264566}, {"type": "node", "id": 198991079, "lat": 40.3725659, "lon": -82.826294}, {"type": "node", "id": 198991080, "lat": 40.372487, "lon": -82.8246377}, {"type": "node", "id": 198991095, "lat": 40.3721271, "lon": -82.8246641}, {"type": "node", "id": 198991096, "lat": 40.3720035, "lon": -82.8246579}, {"type": "node", "id": 198991097, "lat": 40.3718852, "lon": -82.8246332}, {"type": "node", "id": 198991098, "lat": 40.3717345, "lon": -82.824581}, {"type": "node", "id": 198991099, "lat": 40.3716279, "lon": -82.8245054}, {"type": "node", "id": 198991100, "lat": 40.3715415, "lon": -82.8244323}, {"type": "node", "id": 198991101, "lat": 40.3714734, "lon": -82.8243606}, {"type": "node", "id": 198991102, "lat": 40.3714037, "lon": -82.8242778}, {"type": "node", "id": 198991103, "lat": 40.371334, "lon": -82.8241633}, {"type": "node", "id": 198991104, "lat": 40.3712733, "lon": -82.8240522}, {"type": "node", "id": 198991105, "lat": 40.371231, "lon": -82.823962}, {"type": "node", "id": 198991106, "lat": 40.371192, "lon": -82.823841}, {"type": "node", "id": 198991107, "lat": 40.371163, "lon": -82.823715}, {"type": "node", "id": 198991108, "lat": 40.371142, "lon": -82.823588}, {"type": "node", "id": 198991109, "lat": 40.3711265, "lon": -82.8233052}, {"type": "node", "id": 198991110, "lat": 40.3710283, "lon": -82.8217238}, {"type": "node", "id": 198991111, "lat": 40.3710256, "lon": -82.8216009}, {"type": "node", "id": 198991112, "lat": 40.3710333, "lon": -82.8215007}, {"type": "node", "id": 198991113, "lat": 40.371052, "lon": -82.8213741}, {"type": "node", "id": 198991114, "lat": 40.3710757, "lon": -82.8212608}, {"type": "node", "id": 198991115, "lat": 40.3711111, "lon": -82.8211433}, {"type": "node", "id": 198991116, "lat": 40.3711623, "lon": -82.8210218}, {"type": "node", "id": 198991118, "lat": 40.3712249, "lon": -82.8209033}, {"type": "node", "id": 198991120, "lat": 40.3712921, "lon": -82.8208125}, {"type": "node", "id": 198991122, "lat": 40.3713448, "lon": -82.8207472}, {"type": "node", "id": 198991124, "lat": 40.3714046, "lon": -82.8206738}, {"type": "node", "id": 198991126, "lat": 40.3715404, "lon": -82.8205583}, {"type": "node", "id": 198991127, "lat": 40.3716304, "lon": -82.8205081}, {"type": "node", "id": 198991129, "lat": 40.3717085, "lon": -82.8204737}, {"type": "node", "id": 198991131, "lat": 40.3717934, "lon": -82.8204461}, {"type": "node", "id": 198991132, "lat": 40.3719104, "lon": -82.82042}, {"type": "node", "id": 198991134, "lat": 40.3720148, "lon": -82.8204116}, {"type": "node", "id": 198991136, "lat": 40.37322, "lon": -82.8203731, "tags": {"highway": "turning_circle"}}, {"type": "node", "id": 198992064, "lat": 40.3739739, "lon": -82.8245082, "tags": {"highway": "turning_circle"}}, {"type": "node", "id": 229755521, "lat": 40.320081, "lon": -82.843076}, {"type": "node", "id": 229781010, "lat": 40.343109, "lon": -82.83304}, {"type": "node", "id": 229800474, "lat": 40.339072, "lon": -82.834281}, {"type": "node", "id": 229808880, "lat": 40.335929, "lon": -82.835794}, {"type": "node", "id": 229853047, "lat": 40.350396, "lon": -82.831649}, {"type": "node", "id": 229853052, "lat": 40.349403, "lon": -82.831735}, {"type": "node", "id": 229853057, "lat": 40.347075, "lon": -82.831928}, {"type": "node", "id": 229853062, "lat": 40.346729, "lon": -82.831975}, {"type": "node", "id": 229853068, "lat": 40.346417, "lon": -82.832042}, {"type": "node", "id": 229853073, "lat": 40.346108, "lon": -82.832131}, {"type": "node", "id": 229853078, "lat": 40.343357, "lon": -82.83296}, {"type": "node", "id": 229853081, "lat": 40.342957, "lon": -82.83309}, {"type": "node", "id": 229853084, "lat": 40.341187, "lon": -82.833624}, {"type": "node", "id": 229853087, "lat": 40.339352, "lon": -82.834176}, {"type": "node", "id": 229853091, "lat": 40.338762, "lon": -82.834421}, {"type": "node", "id": 229853095, "lat": 40.337923, "lon": -82.83483}, {"type": "node", "id": 229853099, "lat": 40.337073, "lon": -82.835237}, {"type": "node", "id": 229853105, "lat": 40.335299, "lon": -82.836093}, {"type": "node", "id": 229853115, "lat": 40.333807, "lon": -82.836787}, {"type": "node", "id": 229853120, "lat": 40.333041, "lon": -82.837131}, {"type": "node", "id": 229853125, "lat": 40.332645, "lon": -82.837317}, {"type": "node", "id": 229853130, "lat": 40.331517, "lon": -82.837822}, {"type": "node", "id": 229853135, "lat": 40.33113, "lon": -82.838005}, {"type": "node", "id": 229853139, "lat": 40.330043, "lon": -82.838483}, {"type": "node", "id": 229853143, "lat": 40.329174, "lon": -82.838875}, {"type": "node", "id": 229853147, "lat": 40.328374, "lon": -82.83925}, {"type": "node", "id": 229853154, "lat": 40.327439, "lon": -82.839706}, {"type": "node", "id": 229853160, "lat": 40.325856, "lon": -82.840506}, {"type": "node", "id": 229853165, "lat": 40.325309, "lon": -82.840754}, {"type": "node", "id": 229853170, "lat": 40.324084, "lon": -82.841283}, {"type": "node", "id": 229853174, "lat": 40.323476, "lon": -82.841554}, {"type": "node", "id": 229853183, "lat": 40.322347, "lon": -82.842046}, {"type": "node", "id": 229853187, "lat": 40.321426, "lon": -82.842474}, {"type": "node", "id": 229853191, "lat": 40.320377, "lon": -82.842943}, {"type": "node", "id": 229853197, "lat": 40.320256, "lon": -82.842997}, {"type": "node", "id": 229853202, "lat": 40.318746, "lon": -82.843735}, {"type": "node", "id": 229853210, "lat": 40.318292, "lon": -82.843963}, {"type": "node", "id": 229853214, "lat": 40.317629, "lon": -82.844283}, {"type": "node", "id": 229853220, "lat": 40.317325, "lon": -82.844422}, {"type": "node", "id": 229853224, "lat": 40.316952, "lon": -82.844564}, {"type": "node", "id": 229853229, "lat": 40.316758, "lon": -82.844629}, {"type": "node", "id": 229853232, "lat": 40.314732, "lon": -82.845247}, {"type": "node", "id": 229853234, "lat": 40.31381, "lon": -82.845513}, {"type": "node", "id": 229853237, "lat": 40.312504, "lon": -82.845914}, {"type": "node", "id": 229853239, "lat": 40.3119918, "lon": -82.8460806}, {"type": "node", "id": 1708868873, "lat": 40.3735398, "lon": -82.8293511}, {"type": "node", "id": 4532230713, "lat": 40.3788394, "lon": -82.8313599}, {"type": "node", "id": 4532230714, "lat": 40.3774134, "lon": -82.8315018}, {"type": "node", "id": 4532230715, "lat": 40.376344, "lon": -82.8316125}, {"type": "node", "id": 4532230716, "lat": 40.3754252, "lon": -82.8317113}, {"type": "node", "id": 4532230717, "lat": 40.3750155, "lon": -82.8317469}, {"type": "node", "id": 4532230718, "lat": 40.3748709, "lon": -82.8317311}, {"type": "node", "id": 4532230719, "lat": 40.3746902, "lon": -82.8315373}, {"type": "node", "id": 4532230720, "lat": 40.3745094, "lon": -82.8312408}, {"type": "node", "id": 4532230721, "lat": 40.3742503, "lon": -82.8308414}, {"type": "node", "id": 4532230722, "lat": 40.3741419, "lon": -82.8307425}, {"type": "node", "id": 4532230723, "lat": 40.3740154, "lon": -82.8307228}, {"type": "node", "id": 4532230724, "lat": 40.3738196, "lon": -82.8307623}, {"type": "node", "id": 4532230725, "lat": 40.3736388, "lon": -82.8309244}, {"type": "node", "id": 4532230726, "lat": 40.3730634, "lon": -82.8316876}, {"type": "node", "id": 4532230727, "lat": 40.3722048, "lon": -82.8328462}, {"type": "node", "id": 4532230728, "lat": 40.3718102, "lon": -82.8332931}, {"type": "node", "id": 4532230729, "lat": 40.3714079, "lon": -82.8338435}, {"type": "node", "id": 4532230730, "lat": 40.3707829, "lon": -82.834772}, {"type": "node", "id": 4532230731, "lat": 40.3705449, "lon": -82.8351041}, {"type": "node", "id": 4532230732, "lat": 40.370294, "lon": -82.8354442}, {"type": "node", "id": 4532230733, "lat": 40.3700634, "lon": -82.8357766}, {"type": "node", "id": 4532230734, "lat": 40.3698941, "lon": -82.8360729}, {"type": "node", "id": 4532230735, "lat": 40.3696712, "lon": -82.8363339}, {"type": "node", "id": 4532230736, "lat": 40.3694814, "lon": -82.8366226}, {"type": "node", "id": 4532230737, "lat": 40.3694693, "lon": -82.8369231}, {"type": "node", "id": 4532230738, "lat": 40.3694633, "lon": -82.8373423}, {"type": "node", "id": 4532230739, "lat": 40.3694934, "lon": -82.8378524}, {"type": "node", "id": 4532230740, "lat": 40.3696074, "lon": -82.8389251}, {"type": "node", "id": 4532230741, "lat": 40.3697857, "lon": -82.8388963}, {"type": "node", "id": 4532230742, "lat": 40.3699574, "lon": -82.8389358}, {"type": "node", "id": 4532230743, "lat": 40.3700869, "lon": -82.8390821}, {"type": "node", "id": 4532230744, "lat": 40.3701502, "lon": -82.8393075}, {"type": "node", "id": 4532230745, "lat": 40.3708768, "lon": -82.8391872}, {"type": "node", "id": 4532230746, "lat": 40.3715125, "lon": -82.8391279}, {"type": "node", "id": 4532230747, "lat": 40.3719283, "lon": -82.8391121}, {"type": "node", "id": 4532230748, "lat": 40.3723982, "lon": -82.839207}, {"type": "node", "id": 4532230749, "lat": 40.372585, "lon": -82.8392228}, {"type": "node", "id": 4532230750, "lat": 40.3728622, "lon": -82.839207}, {"type": "node", "id": 4532230751, "lat": 40.3701858, "lon": -82.8394561}, {"type": "node", "id": 4532230752, "lat": 40.3701792, "lon": -82.8396427}, {"type": "node", "id": 4532230753, "lat": 40.3701514, "lon": -82.8398395}, {"type": "node", "id": 4532230754, "lat": 40.3701048, "lon": -82.8399837}, {"type": "node", "id": 4532230755, "lat": 40.3697627, "lon": -82.8406949}, {"type": "node", "id": 4532230756, "lat": 40.3694939, "lon": -82.8413743}, {"type": "node", "id": 4532230757, "lat": 40.3692653, "lon": -82.8421089}, {"type": "node", "id": 4532230758, "lat": 40.369108, "lon": -82.8428099}, {"type": "node", "id": 4532230759, "lat": 40.3690247, "lon": -82.8434698}, {"type": "node", "id": 4532230760, "lat": 40.3690224, "lon": -82.8437481, "tags": {"highway": "turning_circle"}}, {"type": "node", "id": 4532230771, "lat": 40.3700999, "lon": -82.8396105}, {"type": "node", "id": 4532230772, "lat": 40.3698749, "lon": -82.839805}, {"type": "node", "id": 4532230773, "lat": 40.3696719, "lon": -82.8399442}, {"type": "node", "id": 4532230774, "lat": 40.369275, "lon": -82.839997}, {"type": "node", "id": 4532230775, "lat": 40.368344, "lon": -82.8400018}, {"type": "node", "id": 4532230776, "lat": 40.3682745, "lon": -82.8399634}, {"type": "node", "id": 4532230777, "lat": 40.3682288, "lon": -82.8398746}, {"type": "node", "id": 4532230778, "lat": 40.368216, "lon": -82.8397425}, {"type": "node", "id": 4532230779, "lat": 40.3682508, "lon": -82.8396417}, {"type": "node", "id": 4532230780, "lat": 40.3684245, "lon": -82.839236}, {"type": "node", "id": 4532230781, "lat": 40.3684794, "lon": -82.8391568}, {"type": "node", "id": 4532230782, "lat": 40.3685855, "lon": -82.8390968}, {"type": "node", "id": 4532230783, "lat": 40.3687044, "lon": -82.839068}, {"type": "node", "id": 4532230784, "lat": 40.3693354, "lon": -82.8389767}, {"type": "node", "id": 4532230785, "lat": 40.3695402, "lon": -82.8389383}, {"type": "node", "id": 4532230786, "lat": 40.3722641, "lon": -82.8329564}, {"type": "node", "id": 4532230787, "lat": 40.3723317, "lon": -82.8331917}, {"type": "node", "id": 4532230788, "lat": 40.3723482, "lon": -82.8334389}, {"type": "node", "id": 4532232089, "lat": 40.3723464, "lon": -82.8337246}, {"type": "node", "id": 4532232090, "lat": 40.3723647, "lon": -82.8342864}, {"type": "node", "id": 4532232091, "lat": 40.3724817, "lon": -82.8367134}, {"type": "node", "id": 4532232092, "lat": 40.3725128, "lon": -82.8373952}, {"type": "node", "id": 4532232093, "lat": 40.3725457, "lon": -82.8379882}, {"type": "node", "id": 4532232094, "lat": 40.3723171, "lon": -82.8380242}, {"type": "node", "id": 4532232095, "lat": 40.3723416, "lon": -82.8391955}, {"type": "node", "id": 4532232096, "lat": 40.3721662, "lon": -82.8379996}, {"type": "node", "id": 4532232098, "lat": 40.3718745, "lon": -82.8337006}, {"type": "node", "id": 4532232099, "lat": 40.3718288, "lon": -82.833499}, {"type": "node", "id": 4532232100, "lat": 40.3718233, "lon": -82.8333669}, {"type": "node", "id": 4532232101, "lat": 40.3720044, "lon": -82.8338735}, {"type": "node", "id": 4532232102, "lat": 40.3721141, "lon": -82.8339023}, {"type": "node", "id": 4532232103, "lat": 40.3722184, "lon": -82.8338807}, {"type": "node", "id": 4532232104, "lat": 40.372286, "lon": -82.833835}, {"type": "node", "id": 4532232105, "lat": 40.3741491, "lon": -82.830642}, {"type": "node", "id": 4532232106, "lat": 40.3747998, "lon": -82.8303533}, {"type": "node", "id": 4532232107, "lat": 40.3750769, "lon": -82.8302426}, {"type": "node", "id": 4532232108, "lat": 40.3754475, "lon": -82.8301872}, {"type": "node", "id": 4532232109, "lat": 40.3761584, "lon": -82.8296732}, {"type": "node", "id": 4532232110, "lat": 40.3761524, "lon": -82.8293924}, {"type": "node", "id": 4532232111, "lat": 40.3761478, "lon": -82.8291359}, {"type": "node", "id": 4532232112, "lat": 40.3763, "lon": -82.8305313}, {"type": "node", "id": 4532232113, "lat": 40.3763934, "lon": -82.8313024}, {"type": "node", "id": 4532232114, "lat": 40.3763939, "lon": -82.8316073}, {"type": "node", "id": 4532232115, "lat": 40.376975, "lon": -82.8290652}, {"type": "node", "id": 4532232116, "lat": 40.3769827, "lon": -82.8294095}, {"type": "node", "id": 4532232117, "lat": 40.3769827, "lon": -82.8295511}, {"type": "node", "id": 4532232118, "lat": 40.3765456, "lon": -82.8295679}, {"type": "node", "id": 4532232119, "lat": 40.3765253, "lon": -82.8291077}, {"type": "node", "id": 4532232120, "lat": 40.3769808, "lon": -82.8293302}, {"type": "node", "id": 4532232121, "lat": 40.3765376, "lon": -82.8293495}, {"type": "node", "id": 4532232122, "lat": 40.3759225, "lon": -82.8291549}, {"type": "node", "id": 4532232123, "lat": 40.3760098, "lon": -82.8289822}, {"type": "node", "id": 4532232124, "lat": 40.3760665, "lon": -82.8288694}, {"type": "node", "id": 4532232125, "lat": 40.3764286, "lon": -82.8288454}, {"type": "node", "id": 4532232126, "lat": 40.3764394, "lon": -82.8291135}, {"type": "node", "id": 4532232127, "lat": 40.376103, "lon": -82.8286533}, {"type": "node", "id": 4532232128, "lat": 40.3764121, "lon": -82.8286413}, {"type": "node", "id": 4532232129, "lat": 40.3707883, "lon": -82.8295857}, {"type": "node", "id": 4532232130, "lat": 40.3708281, "lon": -82.830155}, {"type": "node", "id": 4532232131, "lat": 40.3712725, "lon": -82.830131}, {"type": "node", "id": 4532232132, "lat": 40.3713182, "lon": -82.8308536}, {"type": "node", "id": 4532232133, "lat": 40.3711554, "lon": -82.8308632}, {"type": "node", "id": 4532232134, "lat": 40.3711206, "lon": -82.8301392}, {"type": "node", "id": 4532232135, "lat": 40.3706067, "lon": -82.8301598}, {"type": "node", "id": 4532232136, "lat": 40.3706378, "lon": -82.8305319}, {"type": "node", "id": 4532232137, "lat": 40.3711374, "lon": -82.8304886}, {"type": "node", "id": 4532232138, "lat": 40.3701272, "lon": -82.8296524}, {"type": "node", "id": 4532232139, "lat": 40.3701276, "lon": -82.8301767}, {"type": "node", "id": 4532232140, "lat": 40.3704805, "lon": -82.8313698}, {"type": "node", "id": 4532232141, "lat": 40.3700672, "lon": -82.8317251}, {"type": "node", "id": 4532232142, "lat": 40.3695971, "lon": -82.8317731}, {"type": "node", "id": 4532232143, "lat": 40.3695386, "lon": -82.8302295}, {"type": "node", "id": 4532232144, "lat": 40.3694563, "lon": -82.8301622}, {"type": "node", "id": 4532232145, "lat": 40.3693886, "lon": -82.8300902}, {"type": "node", "id": 4532232146, "lat": 40.3693374, "lon": -82.8299414}, {"type": "node", "id": 4532232147, "lat": 40.3693301, "lon": -82.8297757}, {"type": "node", "id": 4532232148, "lat": 40.3693263, "lon": -82.8297406}, {"type": "node", "id": 4532232149, "lat": 40.3698986, "lon": -82.8301972}, {"type": "node", "id": 4532232150, "lat": 40.3704657, "lon": -82.8313826}, {"type": "node", "id": 4532232151, "lat": 40.3707165, "lon": -82.8312161}, {"type": "node", "id": 4532232152, "lat": 40.3709963, "lon": -82.8311849}, {"type": "node", "id": 4532232153, "lat": 40.3702791, "lon": -82.8296382}, {"type": "node", "id": 4532232154, "lat": 40.3701715, "lon": -82.8279873}, {"type": "node", "id": 4532232155, "lat": 40.3701532, "lon": -82.827668}, {"type": "node", "id": 4532232156, "lat": 40.3701001, "lon": -82.827572}, {"type": "node", "id": 4532232157, "lat": 40.370027, "lon": -82.8275527}, {"type": "node", "id": 4532232158, "lat": 40.3699721, "lon": -82.8276248}, {"type": "node", "id": 4532232159, "lat": 40.3699483, "lon": -82.827752}, {"type": "node", "id": 4532232160, "lat": 40.3699886, "lon": -82.827872}, {"type": "node", "id": 4532232161, "lat": 40.3700562, "lon": -82.827932}, {"type": "node", "id": 4532232162, "lat": 40.3701702, "lon": -82.8279652}, {"type": "node", "id": 4532232163, "lat": 40.3698201, "lon": -82.8296771}, {"type": "node", "id": 4532232164, "lat": 40.3697709, "lon": -82.8288995}, {"type": "node", "id": 4532232165, "lat": 40.3696794, "lon": -82.8286498}, {"type": "node", "id": 4532232206, "lat": 40.3749636, "lon": -82.8315261}, {"type": "node", "id": 4532232207, "lat": 40.3749009, "lon": -82.8303129}, {"type": "node", "id": 4532232208, "lat": 40.3722362, "lon": -82.8400219}, {"type": "node", "id": 4532232209, "lat": 40.372191, "lon": -82.841058}, {"type": "node", "id": 4532232210, "lat": 40.3722844, "lon": -82.8429204}, {"type": "node", "id": 4532232211, "lat": 40.3724803, "lon": -82.8461274}, {"type": "node", "id": 4532232212, "lat": 40.3725887, "lon": -82.8477012}, {"type": "node", "id": 4532232213, "lat": 40.3725706, "lon": -82.8482548}, {"type": "node", "id": 4532232214, "lat": 40.3725224, "lon": -82.8484723}, {"type": "node", "id": 4532232215, "lat": 40.3724501, "lon": -82.8485711}, {"type": "node", "id": 4532232216, "lat": 40.3723959, "lon": -82.8487451}, {"type": "node", "id": 4532232217, "lat": 40.3724321, "lon": -82.8492157}, {"type": "node", "id": 4532232218, "lat": 40.3726271, "lon": -82.8535667, "tags": {"barrier": "gate"}}, {"type": "node", "id": 4532232219, "lat": 40.3726249, "lon": -82.853858}, {"type": "node", "id": 4532232220, "lat": 40.3729662, "lon": -82.8483218}, {"type": "node", "id": 4532232221, "lat": 40.3728005, "lon": -82.8446483}, {"type": "node", "id": 4532232222, "lat": 40.3727131, "lon": -82.8428016}, {"type": "node", "id": 4532232223, "lat": 40.3726077, "lon": -82.8400336}, {"type": "node", "id": 4633676874, "lat": 40.3732965, "lon": -82.8313784}, {"type": "node", "id": 4795306554, "lat": 40.353561, "lon": -82.831331}, {"type": "node", "id": 4795779373, "lat": 40.3807978, "lon": -82.8286701}, {"type": "node", "id": 4993131838, "lat": 40.3786947, "lon": -82.8289186, "tags": {"highway": "traffic_signals", "traffic_signals": "signal"}}, {"type": "node", "id": 6755496656, "lat": 40.3298513, "lon": -82.8385695}, {"type": "node", "id": 6829715438, "lat": 40.338271, "lon": -82.8346604}, {"type": "node", "id": 6829715448, "lat": 40.3403222, "lon": -82.8338841}, {"type": "node", "id": 6829715450, "lat": 40.3410049, "lon": -82.8336788}, {"type": "node", "id": 6829715452, "lat": 40.3422633, "lon": -82.8332993}, {"type": "node", "id": 6837219450, "lat": 40.3486074, "lon": -82.831801}, {"type": "node", "id": 6838061769, "lat": 40.3605363, "lon": -82.8306387}, {"type": "node", "id": 6847374620, "lat": 40.3522789, "lon": -82.8314598}, {"type": "node", "id": 6847374626, "lat": 40.3542326, "lon": -82.8312598}, {"type": "node", "id": 6860315416, "lat": 40.3229696, "lon": -82.8417747}, {"type": "node", "id": 6860315429, "lat": 40.3246124, "lon": -82.8410548}, {"type": "node", "id": 6860315433, "lat": 40.3247067, "lon": -82.8410141}, {"type": "node", "id": 6863668721, "lat": 40.3136223, "lon": -82.8455706}, {"type": "node", "id": 6905275731, "lat": 40.3409399, "lon": -82.8336984}, {"type": "node", "id": 6948391640, "lat": 40.3381709, "lon": -82.8347092}, {"type": "node", "id": 6953395106, "lat": 40.3429363, "lon": -82.8330962}, {"type": "node", "id": 6953755004, "lat": 40.3176819, "lon": -82.8442575}, {"type": "node", "id": 6954112391, "lat": 40.3490594, "lon": -82.8317635}, {"type": "node", "id": 6996437107, "lat": 40.3390671, "lon": -82.8342832}, {"type": "node", "id": 7000621036, "lat": 40.3545107, "lon": -82.8312305}, {"type": "node", "id": 7001207637, "lat": 40.3479496, "lon": -82.8318555}, {"type": "node", "id": 7035322025, "lat": 40.3373327, "lon": -82.8351127}, {"type": "node", "id": 7231952518, "lat": 40.343145, "lon": -82.8330284}, {"type": "node", "id": 7284459988, "lat": 40.3261295, "lon": -82.8403678}, {"type": "node", "id": 7723576028, "lat": 40.3219906, "lon": -82.8422116}, {"type": "node", "id": 7903747504, "lat": 40.3699611, "lon": -82.8361705}, {"type": "node", "id": 7903747505, "lat": 40.3700792, "lon": -82.837521}, {"type": "node", "id": 7903747506, "lat": 40.3700668, "lon": -82.8376352}, {"type": "node", "id": 7903747507, "lat": 40.3700077, "lon": -82.8377005}, {"type": "node", "id": 7908097102, "lat": 40.3678914, "lon": -82.8163601}, {"type": "node", "id": 7908097103, "lat": 40.3679248, "lon": -82.8175624}, {"type": "node", "id": 7908097104, "lat": 40.3679707, "lon": -82.8182058}, {"type": "node", "id": 7908097105, "lat": 40.368032, "lon": -82.8183666}, {"type": "node", "id": 7908443493, "lat": 40.3787607, "lon": -82.8301519}, {"type": "node", "id": 7908443494, "lat": 40.3782099, "lon": -82.8301822}, {"type": "node", "id": 7908443495, "lat": 40.3777135, "lon": -82.8302174}, {"type": "node", "id": 7908443496, "lat": 40.3769864, "lon": -82.8301681}, {"type": "node", "id": 7908443497, "lat": 40.3764176, "lon": -82.8301645}, {"type": "node", "id": 7908443498, "lat": 40.3762422, "lon": -82.8301809}, {"type": "node", "id": 7908443499, "lat": 40.3778632, "lon": -82.8302068}, {"type": "node", "id": 7908443500, "lat": 40.3778369, "lon": -82.8298264}, {"type": "node", "id": 7908443501, "lat": 40.3778208, "lon": -82.8294425}, {"type": "node", "id": 7908443502, "lat": 40.3778437, "lon": -82.8293142}, {"type": "node", "id": 7908443503, "lat": 40.378007, "lon": -82.8292387}, {"type": "node", "id": 7908443504, "lat": 40.3784524, "lon": -82.829207}, {"type": "node", "id": 7908443505, "lat": 40.3785345, "lon": -82.8293545}, {"type": "node", "id": 7908443506, "lat": 40.3785372, "lon": -82.8298123}, {"type": "node", "id": 7908443507, "lat": 40.3784728, "lon": -82.8298687}, {"type": "node", "id": 7908443508, "lat": 40.378328, "lon": -82.8299039}, {"type": "node", "id": 7908443509, "lat": 40.3778442, "lon": -82.8299319}, {"type": "node", "id": 7912229965, "lat": 40.3137586, "lon": -82.8455288}, {"type": "node", "id": 7912229972, "lat": 40.3140368, "lon": -82.8454476}, {"type": "node", "id": 7912229983, "lat": 40.3147738, "lon": -82.8452343}, {"type": "node", "id": 7912720538, "lat": 40.3566356, "lon": -82.8310189}, {"type": "node", "id": 7915525155, "lat": 40.3550358, "lon": -82.8311766}, {"type": "node", "id": 7915693364, "lat": 40.3714793, "lon": -82.8206067}, {"type": "node", "id": 7915693365, "lat": 40.3713484, "lon": -82.8203044}, {"type": "node", "id": 7915693366, "lat": 40.3713162, "lon": -82.8201945}, {"type": "node", "id": 7915693367, "lat": 40.3713097, "lon": -82.8200677}, {"type": "node", "id": 7915693368, "lat": 40.371313, "lon": -82.8198056}, {"type": "node", "id": 7915693369, "lat": 40.3712872, "lon": -82.8193406}, {"type": "node", "id": 7915693370, "lat": 40.3710876, "lon": -82.8160652}, {"type": "node", "id": 7917091623, "lat": 40.3640759, "lon": -82.8303285}, {"type": "node", "id": 7917091624, "lat": 40.3640603, "lon": -82.8301765}, {"type": "node", "id": 7917091625, "lat": 40.3640474, "lon": -82.8300758}, {"type": "node", "id": 7917091626, "lat": 40.3640444, "lon": -82.8299946}, {"type": "node", "id": 7917091627, "lat": 40.3640384, "lon": -82.8298729}, {"type": "node", "id": 7917091628, "lat": 40.3640773, "lon": -82.8297853}, {"type": "node", "id": 7917091629, "lat": 40.3641281, "lon": -82.8296937}, {"type": "node", "id": 7917091630, "lat": 40.364168, "lon": -82.8295929}, {"type": "node", "id": 7917091631, "lat": 40.36419, "lon": -82.8295052}, {"type": "node", "id": 7917091632, "lat": 40.3642059, "lon": -82.8293862}, {"type": "node", "id": 7917091633, "lat": 40.3642159, "lon": -82.8292213}, {"type": "node", "id": 7917091634, "lat": 40.3642807, "lon": -82.8291336}, {"type": "node", "id": 7917091635, "lat": 40.3648305, "lon": -82.8302703}, {"type": "node", "id": 7917091636, "lat": 40.3648087, "lon": -82.8299269}, {"type": "node", "id": 7917091637, "lat": 40.3648035, "lon": -82.8297284}, {"type": "node", "id": 7917091638, "lat": 40.3647986, "lon": -82.8295284}, {"type": "node", "id": 7917091639, "lat": 40.3648121, "lon": -82.8293526}, {"type": "node", "id": 7917091640, "lat": 40.364844, "lon": -82.8291106}, {"type": "node", "id": 7917091641, "lat": 40.3648551, "lon": -82.8289606}, {"type": "node", "id": 7917091642, "lat": 40.3648551, "lon": -82.8287574}, {"type": "node", "id": 7917091643, "lat": 40.3648428, "lon": -82.8284138}, {"type": "node", "id": 7917091644, "lat": 40.3648207, "lon": -82.8281525}, {"type": "node", "id": 7917091645, "lat": 40.3647887, "lon": -82.8279686}, {"type": "node", "id": 7917091646, "lat": 40.3647617, "lon": -82.8278008}, {"type": "node", "id": 7917091647, "lat": 40.3647568, "lon": -82.8275589}, {"type": "node", "id": 7917091648, "lat": 40.3647433, "lon": -82.8274008}, {"type": "node", "id": 7919115282, "lat": 40.370637, "lon": -82.829602}, {"type": "node", "id": 7919115283, "lat": 40.3706366, "lon": -82.8292802}, {"type": "node", "id": 7919115284, "lat": 40.3710922, "lon": -82.829209}, {"type": "node", "id": 7919146085, "lat": 40.371133, "lon": -82.8295571}, {"type": "node", "id": 7919146086, "lat": 40.3706297, "lon": -82.8293115}, {"type": "node", "id": 7919146087, "lat": 40.3706606, "lon": -82.8292633}, {"type": "node", "id": 7919146088, "lat": 40.3711048, "lon": -82.8292308}, {"type": "node", "id": 7919146089, "lat": 40.3710777, "lon": -82.829201}, {"type": "node", "id": 7919928597, "lat": 40.3796788, "lon": -82.8208067}, {"type": "node", "id": 7919928598, "lat": 40.3798563, "lon": -82.8208031}, {"type": "node", "id": 7919928599, "lat": 40.3799122, "lon": -82.8207923}, {"type": "node", "id": 7919928600, "lat": 40.3799668, "lon": -82.820769}, {"type": "node", "id": 7919928601, "lat": 40.3800023, "lon": -82.820735}, {"type": "node", "id": 7919928602, "lat": 40.3800187, "lon": -82.8206866}, {"type": "node", "id": 7919928603, "lat": 40.3800269, "lon": -82.8206185}, {"type": "node", "id": 7919928604, "lat": 40.3800241, "lon": -82.8204931}, {"type": "node", "id": 7919928605, "lat": 40.3799873, "lon": -82.8197424}, {"type": "node", "id": 7919928606, "lat": 40.3799382, "lon": -82.818981}, {"type": "node", "id": 7919928607, "lat": 40.3798849, "lon": -82.8178935}, {"type": "node", "id": 7919928608, "lat": 40.3798276, "lon": -82.8168992}, {"type": "node", "id": 7919928609, "lat": 40.3797867, "lon": -82.8158152}, {"type": "node", "id": 7919928610, "lat": 40.3797826, "lon": -82.8157472}, {"type": "node", "id": 7919928611, "lat": 40.3797592, "lon": -82.8155585}, {"type": "node", "id": 7920355306, "lat": 40.3310905, "lon": -82.8380224}, {"type": "node", "id": 7927395280, "lat": 40.3767939, "lon": -82.8162075}, {"type": "node", "id": 7927395281, "lat": 40.3768399, "lon": -82.8165102}, {"type": "node", "id": 7927395282, "lat": 40.376875, "lon": -82.8168765}, {"type": "node", "id": 7927395283, "lat": 40.3768836, "lon": -82.8170249}, {"type": "node", "id": 7927395284, "lat": 40.3768859, "lon": -82.8171006}, {"type": "node", "id": 7927399685, "lat": 40.3768696, "lon": -82.8171763}, {"type": "node", "id": 7927399686, "lat": 40.376822, "lon": -82.8171998}, {"type": "node", "id": 7927399687, "lat": 40.3767737, "lon": -82.817205}, {"type": "node", "id": 7927399688, "lat": 40.3766443, "lon": -82.8171998}, {"type": "node", "id": 7927399689, "lat": 40.3765273, "lon": -82.8171927}, {"type": "node", "id": 7927399690, "lat": 40.3764541, "lon": -82.8171927}, {"type": "node", "id": 7927399691, "lat": 40.3764073, "lon": -82.8172029}, {"type": "node", "id": 7927399692, "lat": 40.3763597, "lon": -82.8172357}, {"type": "node", "id": 7927399693, "lat": 40.3763048, "lon": -82.817294}, {"type": "node", "id": 7927399694, "lat": 40.3762822, "lon": -82.817339}, {"type": "node", "id": 7927399695, "lat": 40.3762678, "lon": -82.8174004}, {"type": "node", "id": 7927399696, "lat": 40.3762654, "lon": -82.8174715}, {"type": "node", "id": 7927399697, "lat": 40.376281, "lon": -82.8176005}, {"type": "node", "id": 7927399698, "lat": 40.3763293, "lon": -82.8178087}, {"type": "node", "id": 7927399699, "lat": 40.3763788, "lon": -82.818018}, {"type": "node", "id": 7927399700, "lat": 40.3764131, "lon": -82.8181305}, {"type": "node", "id": 7927399701, "lat": 40.3764584, "lon": -82.8182165}, {"type": "node", "id": 7927423682, "lat": 40.3478852, "lon": -82.8318608}, {"type": "node", "id": 7936348508, "lat": 40.372347, "lon": -82.8336325}, {"type": "node", "id": 7936348509, "lat": 40.3726262, "lon": -82.8338665}, {"type": "node", "id": 7936348510, "lat": 40.3727805, "lon": -82.834051}, {"type": "node", "id": 7936348511, "lat": 40.3728113, "lon": -82.8344245}, {"type": "node", "id": 7936348512, "lat": 40.3728868, "lon": -82.8360128}, {"type": "node", "id": 7936348513, "lat": 40.3729313, "lon": -82.8371647}, {"type": "node", "id": 7936348514, "lat": 40.372969, "lon": -82.8379702}, {"type": "node", "id": 7936348515, "lat": 40.3729999, "lon": -82.8383526}, {"type": "node", "id": 7936348516, "lat": 40.3730376, "lon": -82.8391626}, {"type": "node", "id": 7936348517, "lat": 40.3730753, "lon": -82.839689}, {"type": "node", "id": 7936348518, "lat": 40.373089, "lon": -82.8401165}, {"type": "node", "id": 7936348519, "lat": 40.3726109, "lon": -82.8401177}, {"type": "node", "id": 7940648151, "lat": 40.3595116, "lon": -82.8307402}, {"type": "node", "id": 8006515666, "lat": 40.3555554, "lon": -82.8311254}, {"type": "node", "id": 8006515674, "lat": 40.3558702, "lon": -82.8310943}, {"type": "node", "id": 8006515675, "lat": 40.3572465, "lon": -82.8309604}, {"type": "node", "id": 8008881061, "lat": 40.3307893, "lon": -82.8381548}, {"type": "node", "id": 8008881067, "lat": 40.3320935, "lon": -82.8375639}, {"type": "node", "id": 8009561655, "lat": 40.3531929, "lon": -82.831368}, {"type": "node", "id": 8009561664, "lat": 40.3528891, "lon": -82.8313985}, {"type": "node", "id": 8021442544, "lat": 40.3369608, "lon": -82.8352916}, {"type": "node", "id": 8034753152, "lat": 40.3725255, "lon": -82.8254451}, {"type": "node", "id": 8034753153, "lat": 40.3728583, "lon": -82.8254167}, {"type": "node", "id": 8034753154, "lat": 40.3729452, "lon": -82.8253846}, {"type": "node", "id": 8034753155, "lat": 40.3729968, "lon": -82.8253026}, {"type": "node", "id": 8034753156, "lat": 40.3730375, "lon": -82.8252064}, {"type": "node", "id": 8034753157, "lat": 40.3730457, "lon": -82.8251101}, {"type": "node", "id": 8034753158, "lat": 40.3730267, "lon": -82.8245939}, {"type": "node", "id": 8034753159, "lat": 40.3737607, "lon": -82.8259289}, {"type": "node", "id": 8034753160, "lat": 40.3737177, "lon": -82.825094}, {"type": "node", "id": 8034753161, "lat": 40.3736864, "lon": -82.8245365}, {"type": "node", "id": 8034753162, "lat": 40.3745249, "lon": -82.8244484}, {"type": "node", "id": 8034753163, "lat": 40.3750752, "lon": -82.8243726}, {"type": "node", "id": 8034753164, "lat": 40.3751363, "lon": -82.8244128}, {"type": "node", "id": 8034753165, "lat": 40.3751635, "lon": -82.8244797}, {"type": "node", "id": 8034753166, "lat": 40.3751771, "lon": -82.824716}, {"type": "node", "id": 8034753167, "lat": 40.3751941, "lon": -82.8252911}, {"type": "node", "id": 8034753168, "lat": 40.3751608, "lon": -82.824348}, {"type": "node", "id": 8034753169, "lat": 40.3755303, "lon": -82.8242596}, {"type": "node", "id": 8049627617, "lat": 40.343921, "lon": -82.83279}, {"type": "node", "id": 8058009968, "lat": 40.3776971, "lon": -82.8296287}, {"type": "node", "id": 8058009969, "lat": 40.3776795, "lon": -82.8293852}, {"type": "node", "id": 8058009970, "lat": 40.3776444, "lon": -82.8292832}, {"type": "node", "id": 8058009971, "lat": 40.3775692, "lon": -82.8292305}, {"type": "node", "id": 8058009972, "lat": 40.3774689, "lon": -82.8292141}, {"type": "node", "id": 8058009973, "lat": 40.3772332, "lon": -82.8292865}, {"type": "node", "id": 8058009974, "lat": 40.377153, "lon": -82.8293424}, {"type": "node", "id": 8058009975, "lat": 40.3771254, "lon": -82.8293786}, {"type": "node", "id": 8058009976, "lat": 40.3771204, "lon": -82.8294839}, {"type": "node", "id": 8058009977, "lat": 40.3771405, "lon": -82.8297834}, {"type": "node", "id": 8058009978, "lat": 40.377158, "lon": -82.8298459}, {"type": "node", "id": 8058009979, "lat": 40.3771856, "lon": -82.829892}, {"type": "node", "id": 8058009980, "lat": 40.3772357, "lon": -82.8299151}, {"type": "node", "id": 8058009981, "lat": 40.3774213, "lon": -82.8298986}, {"type": "node", "id": 8058009982, "lat": 40.3777042, "lon": -82.8298828}, {"type": "node", "id": 8061875276, "lat": 40.3744595, "lon": -82.8244555}, {"type": "node", "id": 8080617420, "lat": 40.368691, "lon": -82.8298208}, {"type": "node", "id": 8080617421, "lat": 40.368681, "lon": -82.8297754}, {"type": "node", "id": 8080617422, "lat": 40.3686755, "lon": -82.8297548}, {"type": "node", "id": 8080617423, "lat": 40.3686685, "lon": -82.8297199}, {"type": "node", "id": 8080617424, "lat": 40.3686677, "lon": -82.8296799}, {"type": "node", "id": 8080617425, "lat": 40.3686661, "lon": -82.829334}, {"type": "node", "id": 8080617426, "lat": 40.3686622, "lon": -82.8292858}, {"type": "node", "id": 8080617427, "lat": 40.3686552, "lon": -82.8292468}, {"type": "node", "id": 8080617428, "lat": 40.3686458, "lon": -82.8291986}, {"type": "node", "id": 8080617429, "lat": 40.368645, "lon": -82.8291616}, {"type": "node", "id": 8080617430, "lat": 40.3686458, "lon": -82.8291329}, {"type": "node", "id": 8080617431, "lat": 40.3686552, "lon": -82.829099}, {"type": "node", "id": 8221336356, "lat": 40.3792117, "lon": -82.8383616, "tags": {"highway": "turning_circle"}}, {"type": "node", "id": 8221336357, "lat": 40.3791651, "lon": -82.8374856}, {"type": "node", "id": 8221336358, "lat": 40.3823634, "lon": -82.8371503}, {"type": "node", "id": 8221336359, "lat": 40.3825165, "lon": -82.8370388}, {"type": "node", "id": 8221336360, "lat": 40.3825758, "lon": -82.836868}, {"type": "node", "id": 8221336361, "lat": 40.3825873, "lon": -82.8365927}, {"type": "node", "id": 8221336362, "lat": 40.3824176, "lon": -82.8339187}, {"type": "node", "id": 8221336363, "lat": 40.3843673, "lon": -82.8358208}, {"type": "node", "id": 8221336364, "lat": 40.3796232, "lon": -82.8362849}, {"type": "node", "id": 8221336365, "lat": 40.379353, "lon": -82.831528}, {"type": "node", "id": 8221336366, "lat": 40.3794554, "lon": -82.8312789}, {"type": "node", "id": 8221336367, "lat": 40.379543, "lon": -82.8312347}, {"type": "node", "id": 8221336368, "lat": 40.3796324, "lon": -82.8311151}, {"type": "node", "id": 8221336369, "lat": 40.3797235, "lon": -82.8309977}, {"type": "node", "id": 8221336370, "lat": 40.3798315, "lon": -82.8309048}, {"type": "node", "id": 8221336371, "lat": 40.37992, "lon": -82.8308397}, {"type": "node", "id": 8221336372, "lat": 40.384499, "lon": -82.8304037}, {"type": "node", "id": 8221336373, "lat": 40.3825496, "lon": -82.8359986}, {"type": "node", "id": 8310781856, "lat": 40.350403, "lon": -82.8316483}, {"type": "node", "id": 8313982877, "lat": 40.3705765, "lon": -82.8285149}, {"type": "node", "id": 8313982878, "lat": 40.3705984, "lon": -82.828389}, {"type": "node", "id": 8313982879, "lat": 40.3706557, "lon": -82.8283381}, {"type": "node", "id": 8313982880, "lat": 40.3718527, "lon": -82.8282209}, {"type": "node", "id": 8314220785, "lat": 40.3721524, "lon": -82.8376492}, {"type": "node", "id": 8314220786, "lat": 40.3716794, "lon": -82.8376136}, {"type": "node", "id": 8314220787, "lat": 40.3715904, "lon": -82.8376019}, {"type": "node", "id": 8314220788, "lat": 40.3714835, "lon": -82.8375357}, {"type": "node", "id": 8314220789, "lat": 40.3707086, "lon": -82.8365809}, {"type": "node", "id": 8314220790, "lat": 40.370373, "lon": -82.8361288}, {"type": "node", "id": 8314220791, "lat": 40.3716442, "lon": -82.837609}, {"type": "node", "id": 8314220792, "lat": 40.3714479, "lon": -82.8342543}, {"type": "node", "id": 8314220793, "lat": 40.3716066, "lon": -82.8369669}, {"type": "node", "id": 8314220794, "lat": 40.3714955, "lon": -82.8368999}, {"type": "node", "id": 8314220795, "lat": 40.3715657, "lon": -82.8362689}, {"type": "node", "id": 8314220796, "lat": 40.3714307, "lon": -82.8361479}, {"type": "node", "id": 8314220797, "lat": 40.3715267, "lon": -82.8356013}, {"type": "node", "id": 8314220798, "lat": 40.3710789, "lon": -82.835102}, {"type": "node", "id": 8314220799, "lat": 40.3714845, "lon": -82.8348797}, {"type": "node", "id": 8314686708, "lat": 40.3734635, "lon": -82.8482113}, {"type": "node", "id": 8314686709, "lat": 40.3734291, "lon": -82.8475726}, {"type": "node", "id": 8314686710, "lat": 40.3733844, "lon": -82.8467134}, {"type": "node", "id": 8314686711, "lat": 40.373331, "lon": -82.8455437}, {"type": "node", "id": 8314686712, "lat": 40.3732921, "lon": -82.844692}, {"type": "node", "id": 8314686713, "lat": 40.3732633, "lon": -82.8439501}, {"type": "node", "id": 8314686714, "lat": 40.3732243, "lon": -82.8431136}, {"type": "node", "id": 8314686715, "lat": 40.3731782, "lon": -82.8422638}, {"type": "node", "id": 8314686716, "lat": 40.3731306, "lon": -82.8411661}, {"type": "node", "id": 8314690917, "lat": 40.3730989, "lon": -82.840481}, {"type": "node", "id": 8339109117, "lat": 40.3712188, "lon": -82.8206914}, {"type": "node", "id": 8339109118, "lat": 40.3712668, "lon": -82.8204444}, {"type": "node", "id": 8340859021, "lat": 40.3755065, "lon": -82.8303177}, {"type": "node", "id": 8340859022, "lat": 40.3756931, "lon": -82.8307059}, {"type": "node", "id": 8340859023, "lat": 40.3757735, "lon": -82.8307875}, {"type": "node", "id": 8340859024, "lat": 40.3758504, "lon": -82.8308646}, {"type": "node", "id": 8340859025, "lat": 40.3758915, "lon": -82.8309393}, {"type": "node", "id": 8340859026, "lat": 40.3759238, "lon": -82.8310618}, {"type": "node", "id": 8340859027, "lat": 40.375973, "lon": -82.8314007}, {"type": "node", "id": 8340859028, "lat": 40.3760001, "lon": -82.8316495}, {"type": "node", "id": 8583841015, "lat": 40.3619732, "lon": -82.8304974}, {"type": "node", "id": 8584664263, "lat": 40.3622112, "lon": -82.8304746}, {"type": "node", "id": 8654335451, "lat": 40.3470914, "lon": -82.8319266}, {"type": "node", "id": 8735332087, "lat": 40.3778113, "lon": -82.8289886}, {"type": "node", "id": 8735355825, "lat": 40.3730608, "lon": -82.8203368}, {"type": "node", "id": 9027871775, "lat": 40.3733685, "lon": -82.8202297}, {"type": "node", "id": 9027871776, "lat": 40.3735249, "lon": -82.8201658}, {"type": "node", "id": 9027871777, "lat": 40.3739561, "lon": -82.8201293}, {"type": "node", "id": 9027871778, "lat": 40.3743386, "lon": -82.8200745}, {"type": "node", "id": 9027871779, "lat": 40.3744391, "lon": -82.8200642}, {"type": "node", "id": 9027871780, "lat": 40.3747433, "lon": -82.820032}, {"type": "node", "id": 9027871781, "lat": 40.3748845, "lon": -82.8200283}, {"type": "node", "id": 9027871782, "lat": 40.3749467, "lon": -82.8201025}, {"type": "node", "id": 9027871783, "lat": 40.3750173, "lon": -82.8208959}, {"type": "node", "id": 9027871784, "lat": 40.3749806, "lon": -82.8209626}, {"type": "node", "id": 9027871785, "lat": 40.3748873, "lon": -82.8210108}, {"type": "node", "id": 9027871786, "lat": 40.3744552, "lon": -82.821022}, {"type": "node", "id": 9027871787, "lat": 40.3743648, "lon": -82.8209849}, {"type": "node", "id": 9027871788, "lat": 40.3742773, "lon": -82.8208662}, {"type": "node", "id": 9027871789, "lat": 40.3738637, "lon": -82.8201371}, {"type": "node", "id": 9188122581, "lat": 40.3118161, "lon": -82.846132}, {"type": "node", "id": 11013854996, "lat": 40.3720071, "lon": -82.8277923}, {"type": "node", "id": 11013854997, "lat": 40.3727909, "lon": -82.8284143}, {"type": "node", "id": 11013854998, "lat": 40.3727998, "lon": -82.8285035}, {"type": "node", "id": 11013854999, "lat": 40.3725275, "lon": -82.829054}, {"type": "node", "id": 11013855000, "lat": 40.3724884, "lon": -82.8290738}, {"type": "node", "id": 11013855001, "lat": 40.3724135, "lon": -82.8290699}, {"type": "node", "id": 11013855002, "lat": 40.3717858, "lon": -82.8285786}, {"type": "node", "id": 11013855003, "lat": 40.3721451, "lon": -82.8288599}, {"type": "node", "id": 11013855004, "lat": 40.3724616, "lon": -82.828153}, {"type": "node", "id": 11013877805, "lat": 40.3719882, "lon": -82.828737}, {"type": "node", "id": 11013877806, "lat": 40.3722963, "lon": -82.8280218}, {"type": "node", "id": 11013877807, "lat": 40.3724079, "lon": -82.8282729}, {"type": "node", "id": 11013877808, "lat": 40.3723742, "lon": -82.8282483}, {"type": "node", "id": 11013877809, "lat": 40.3722956, "lon": -82.8281886}, {"type": "node", "id": 11013877810, "lat": 40.3722425, "lon": -82.8281465}, {"type": "node", "id": 11013877811, "lat": 40.3722215, "lon": -82.8286892}, {"type": "node", "id": 11013877812, "lat": 40.3721789, "lon": -82.8286604}, {"type": "node", "id": 11013877813, "lat": 40.372103, "lon": -82.8286019}, {"type": "node", "id": 11013877814, "lat": 40.3720611, "lon": -82.8285678}, {"type": "node", "id": 11013877815, "lat": 40.3722622, "lon": -82.8285984}, {"type": "node", "id": 11013877816, "lat": 40.3722235, "lon": -82.8285718}, {"type": "node", "id": 11013877817, "lat": 40.3721438, "lon": -82.8285151}, {"type": "node", "id": 11013877818, "lat": 40.3720981, "lon": -82.8284818}, {"type": "node", "id": 11013877819, "lat": 40.3722967, "lon": -82.8285213}, {"type": "node", "id": 11013877820, "lat": 40.372256, "lon": -82.8284914}, {"type": "node", "id": 11013877821, "lat": 40.3721873, "lon": -82.8284397}, {"type": "node", "id": 11013877822, "lat": 40.3721328, "lon": -82.8284012}, {"type": "node", "id": 11013877823, "lat": 40.3723302, "lon": -82.8284465}, {"type": "node", "id": 11013877824, "lat": 40.3722895, "lon": -82.8284121}, {"type": "node", "id": 11013877825, "lat": 40.3722212, "lon": -82.8283567}, {"type": "node", "id": 11013877826, "lat": 40.3721689, "lon": -82.8283175}, {"type": "node", "id": 11013877827, "lat": 40.3723661, "lon": -82.8283662}, {"type": "node", "id": 11013877828, "lat": 40.37233, "lon": -82.8283399}, {"type": "node", "id": 11013877829, "lat": 40.3722575, "lon": -82.8282846}, {"type": "node", "id": 11013877830, "lat": 40.3722018, "lon": -82.8282412}, {"type": "node", "id": 11013877831, "lat": 40.372506, "lon": -82.828072}, {"type": "node", "id": 11013877832, "lat": 40.3725357, "lon": -82.8280493}, {"type": "node", "id": 11013877833, "lat": 40.3725764, "lon": -82.8280412}, {"type": "node", "id": 11013877834, "lat": 40.372608, "lon": -82.8280527}, {"type": "node", "id": 11013877835, "lat": 40.372747, "lon": -82.8281641}, {"type": "node", "id": 11013877836, "lat": 40.3727663, "lon": -82.8281971}, {"type": "node", "id": 11013877837, "lat": 40.3727685, "lon": -82.8282374}, {"type": "node", "id": 11013877838, "lat": 40.3727624, "lon": -82.8282853}, {"type": "node", "id": 11013877839, "lat": 40.3727333, "lon": -82.8283686}, {"type": "node", "id": 11086159163, "lat": 40.3702979, "lon": -82.8307484}, {"type": "node", "id": 11086159164, "lat": 40.3703297, "lon": -82.8308558}, {"type": "node", "id": 11099275670, "lat": 40.3723562, "lon": -82.8297851}, {"type": "node", "id": 11099275671, "lat": 40.3719842, "lon": -82.8298051}, {"type": "node", "id": 11099275672, "lat": 40.3719795, "lon": -82.8304968}, {"type": "node", "id": 11099275673, "lat": 40.3720757, "lon": -82.8298002}, {"type": "node", "id": 11099275674, "lat": 40.3720603, "lon": -82.8294711}, {"type": "node", "id": 11099275675, "lat": 40.3723445, "lon": -82.8299869}, {"type": "node", "id": 11099275676, "lat": 40.3719828, "lon": -82.8300007}, {"type": "node", "id": 11099275677, "lat": 40.37227, "lon": -82.8299897}, {"type": "node", "id": 11099275678, "lat": 40.3722692, "lon": -82.8299652}, {"type": "node", "id": 11099275679, "lat": 40.3722698, "lon": -82.829842}, {"type": "node", "id": 11099275680, "lat": 40.3722699, "lon": -82.8297897}, {"type": "node", "id": 11099275681, "lat": 40.3721865, "lon": -82.8299929}, {"type": "node", "id": 11099275682, "lat": 40.3721853, "lon": -82.8299652}, {"type": "node", "id": 11099275683, "lat": 40.372183, "lon": -82.8298412}, {"type": "node", "id": 11099275684, "lat": 40.3721818, "lon": -82.8297944}, {"type": "node", "id": 11099275685, "lat": 40.3721114, "lon": -82.8299958}, {"type": "node", "id": 11099275686, "lat": 40.3721102, "lon": -82.8299691}, {"type": "node", "id": 11099275687, "lat": 40.3721108, "lon": -82.8298389}, {"type": "node", "id": 11099275688, "lat": 40.3721115, "lon": -82.8297982}, {"type": "node", "id": 11978057595, "lat": 40.3680663, "lon": -82.8299054}, {"type": "node", "id": 11978057596, "lat": 40.3682032, "lon": -82.8320917}, {"type": "node", "id": 11978057597, "lat": 40.3682729, "lon": -82.8322181}, {"type": "node", "id": 11978057598, "lat": 40.3686378, "lon": -82.8321851}, {"type": "node", "id": 11978057599, "lat": 40.3681593, "lon": -82.8313961}, {"type": "node", "id": 11978057600, "lat": 40.3685683, "lon": -82.8313684}, {"type": "node", "id": 11978057601, "lat": 40.3681861, "lon": -82.8318196}, {"type": "node", "id": 11978057602, "lat": 40.3686206, "lon": -82.831769}, {"type": "way", "id": 19185270, "nodes": [198976035, 198991050, 198991052, 198991054, 11013855002, 8313982880, 198991056, 198991063, 11013854996, 198991065, 198991069, 198991072, 198991074, 198991079, 8034753152, 198991080, 198991095, 198991096, 198991097, 198991098, 198991099, 198991100, 198991101, 198991102, 198991103, 198991104, 198991105, 198991106, 198991107, 198991108, 198991109, 198991110, 198991111, 198991112, 198991113, 198991114, 198991115, 198991116, 198991118, 198991120, 198991122, 198991124, 7915693364, 198991126, 198991127, 198991129, 198991131, 198991132, 198991134, 8735355825, 198991136], "tags": {"highway": "residential", "lit": "no", "name": "Bennington Way", "name_1": "Township Highway 256", "ref": "T-256", "surface": "asphalt", "tiger:cfcc": "A41", "tiger:county": "Morrow, OH", "tiger:name_base": "Bennington", "tiger:name_base_1": "Township Highway 256", "tiger:name_type": "Way", "tiger:reviewed": "yes"}}, {"type": "way", "id": 19185326, "nodes": [198991080, 8034753158, 8034753161, 198992064], "tags": {"highway": "residential", "lit": "no", "name": "Industrial Way", "name_1": "Township Highway 257", "ref": "T-256", "tiger:cfcc": "A41", "tiger:county": "Morrow, OH", "tiger:name_base": "Industrial", "tiger:name_base_1": "Township Highway 257", "tiger:name_type": "Way", "tiger:reviewed": "yes"}}, {"type": "way", "id": 158741579, "nodes": [1708868873, 198970761], "tags": {"destination:backward": "Marengo;Mount Gilead;Cardington;Galion", "hgv": "designated", "hgv:national_network": "yes", "highway": "primary", "lanes": "3", "lanes:backward": "1", "lanes:forward": "2", "lit": "no", "maxspeed": "45 mph", "name": "State Route 61", "old_ref:fap": "32", "ref": "SR 61", "source:hgv:national_network": "Title 23: Highways Part 658 http://ecfr.gpoaccess.gov/cgi/t/text/text-idx?c=ecfr&rgn=div5&view=text&node=23:1.0.1.7.33&idno=23", "source:old_ref:fap": "ODOT http://www.dot.state.oh.us/Divisions/Planning/TechServ/prod_services/Pages/RI06.aspx http://www.dot.state.oh.us/Divisions/ContractAdmin/Contracts/Pages/NHS-FAP.aspx", "surface": "asphalt", "tiger:cfcc": "A31", "tiger:county": "Delaware, OH:Morrow, OH", "tiger:name_base": "State Route 61", "tiger:reviewed": "yes", "tiger:zip_left": "43074:43315", "tiger:zip_right": "43074:43315", "turn:lanes:forward": "left|"}}, {"type": "way", "id": 158741600, "nodes": [198976043, 1708868873], "tags": {"bridge": "yes", "hgv": "designated", "hgv:national_network": "yes", "highway": "primary", "lanes": "3", "lanes:backward": "2", "lanes:forward": "1", "layer": "1", "lit": "no", "maxspeed": "45 mph", "name": "State Route 61", "old_ref:fap": "32", "ref": "SR 61", "source:hgv:national_network": "Title 23: Highways Part 658 http://ecfr.gpoaccess.gov/cgi/t/text/text-idx?c=ecfr&rgn=div5&view=text&node=23:1.0.1.7.33&idno=23", "source:old_ref:fap": "ODOT http://www.dot.state.oh.us/Divisions/Planning/TechServ/prod_services/Pages/RI06.aspx http://www.dot.state.oh.us/Divisions/ContractAdmin/Contracts/Pages/NHS-FAP.aspx", "surface": "asphalt", "tiger:cfcc": "A31", "tiger:county": "Delaware, OH:Morrow, OH", "tiger:name_base": "State Route 61", "tiger:reviewed": "yes", "tiger:zip_left": "43074:43315", "tiger:zip_right": "43074:43315", "turn:lanes:backward": "left|through"}}, {"type": "way", "id": 457006292, "nodes": [4993131838, 7908443493, 4532230713, 4532230714, 4532232114, 4532230715, 8340859028, 4532230716, 4532230717, 4532230718, 4532230719, 4532230720, 4532230721, 4532230722, 4532230723, 4532230724, 4532230725, 4633676874, 4532230726, 4532230727, 4532230728, 4532230729, 4532230730, 4532230731, 4532230732], "tags": {"highway": "unclassified", "name": "Cardinal Drive"}}, {"type": "way", "id": 457006294, "nodes": [4532230751, 4532230771, 4532230772, 4532230773, 4532230774, 4532230775, 4532230776, 4532230777, 4532230778, 4532230779, 4532230780, 4532230781, 4532230782, 4532230783, 4532230784, 4532230785, 4532230740], "tags": {"highway": "residential"}}, {"type": "way", "id": 457006295, "nodes": [4532230727, 4532230786, 4532230787, 4532230788, 7936348508, 4532232089, 4532232090, 4532232091, 4532232092, 4532232093, 4532232094, 4532232095, 4532232208, 4532232209, 4532232210, 4532232211, 4532232212, 4532232213, 4532232214, 4532232215, 4532232216, 4532232217, 4532232218, 4532232219, 198977862], "tags": {"highway": "unclassified"}}, {"type": "way", "id": 457006296, "nodes": [4532232094, 4532232096, 8314220785, 4532232101, 4532232098, 4532232099, 4532232100, 4532230728], "tags": {"highway": "unclassified"}}, {"type": "way", "id": 457006297, "nodes": [4532232101, 4532232102, 4532232103, 4532232104, 4532232089], "tags": {"highway": "unclassified"}}, {"type": "way", "id": 457006298, "nodes": [4532230723, 4532232105, 4532232106, 4532232207, 4532232107, 4532232108, 4532232109, 4532232110, 4532232111], "tags": {"highway": "service"}}, {"type": "way", "id": 457006299, "nodes": [4532232109, 7908443498, 4532232112, 4532232113, 4532232114], "tags": {"highway": "service"}}, {"type": "way", "id": 457006300, "nodes": [4532232115, 4532232120, 4532232116, 4532232117, 4532232118, 4532232121, 4532232119], "tags": {"highway": "service"}}, {"type": "way", "id": 457006301, "nodes": [4532232120, 4532232121], "tags": {"highway": "service"}}, {"type": "way", "id": 457006302, "nodes": [4532232122, 4532232123, 4532232124, 4532232125, 4532232126], "tags": {"highway": "service"}}, {"type": "way", "id": 457006303, "nodes": [4532232124, 4532232127, 4532232128, 4532232125], "tags": {"highway": "service"}}, {"type": "way", "id": 457006304, "nodes": [4532232129, 4532232130, 4532232134, 4532232131, 4532232132, 4532232133, 4532232137, 4532232134], "tags": {"highway": "service"}}, {"type": "way", "id": 457006305, "nodes": [4532232130, 4532232135, 4532232136, 4532232137], "tags": {"highway": "service"}}, {"type": "way", "id": 457006306, "nodes": [11086159164, 4532232140, 4532232150, 4532232141, 4532232142, 4532232143, 4532232144, 4532232145, 4532232146, 4532232147, 4532232148], "tags": {"highway": "service", "service": "parking_aisle"}}, {"type": "way", "id": 457006307, "nodes": [4532232139, 4532232149, 4532232143], "tags": {"highway": "service"}}, {"type": "way", "id": 457006308, "nodes": [4532232149, 4532232141], "tags": {"highway": "service", "service": "parking_aisle"}}, {"type": "way", "id": 457006309, "nodes": [4532232150, 4532232151, 4532232152], "tags": {"highway": "service", "service": "parking_aisle"}}, {"type": "way", "id": 457006310, "nodes": [4532232153, 4532232154, 4532232162, 4532232155, 4532232156, 4532232157, 4532232158, 4532232159, 4532232160, 4532232161, 4532232162], "tags": {"highway": "residential"}}, {"type": "way", "id": 457006311, "nodes": [4532232163, 4532232164, 4532232165], "tags": {"highway": "service"}}, {"type": "way", "id": 457006319, "nodes": [4532230717, 4532232206, 4532232207], "tags": {"highway": "track"}}, {"type": "way", "id": 457006320, "nodes": [4532232214, 4532232220, 4532232221, 4532232222, 7936348519, 4532232223, 4532232095], "tags": {"highway": "service", "service": "parking_aisle"}}, {"type": "way", "id": 487061352, "nodes": [198970761, 11099275674, 198976035], "tags": {"hgv": "designated", "hgv:national_network": "yes", "highway": "primary", "lanes": "2", "lit": "no", "maxspeed": "45 mph", "name": "State Route 61", "old_ref:fap": "32", "ref": "SR 61", "source:hgv:national_network": "Title 23: Highways Part 658 http://ecfr.gpoaccess.gov/cgi/t/text/text-idx?c=ecfr&rgn=div5&view=text&node=23:1.0.1.7.33&idno=23", "source:old_ref:fap": "ODOT http://www.dot.state.oh.us/Divisions/Planning/TechServ/prod_services/Pages/RI06.aspx http://www.dot.state.oh.us/Divisions/ContractAdmin/Contracts/Pages/NHS-FAP.aspx", "surface": "asphalt", "tiger:cfcc": "A31", "tiger:county": "Delaware, OH:Morrow, OH", "tiger:name_base": "State Route 61", "tiger:reviewed": "yes", "tiger:zip_left": "43074:43315", "tiger:zip_right": "43074:43315"}}, {"type": "way", "id": 487061355, "nodes": [198967387, 198976043], "tags": {"hgv": "designated", "hgv:national_network": "yes", "highway": "primary", "lanes": "3", "lanes:backward": "2", "lanes:forward": "1", "lit": "no", "maxspeed": "45 mph", "name": "State Route 61", "old_ref:fap": "32", "ref": "SR 61", "source:hgv:national_network": "Title 23: Highways Part 658 http://ecfr.gpoaccess.gov/cgi/t/text/text-idx?c=ecfr&rgn=div5&view=text&node=23:1.0.1.7.33&idno=23", "source:old_ref:fap": "ODOT http://www.dot.state.oh.us/Divisions/Planning/TechServ/prod_services/Pages/RI06.aspx http://www.dot.state.oh.us/Divisions/ContractAdmin/Contracts/Pages/NHS-FAP.aspx", "surface": "asphalt", "tiger:cfcc": "A31", "tiger:county": "Delaware, OH:Morrow, OH", "tiger:name_base": "State Route 61", "tiger:reviewed": "yes", "tiger:zip_left": "43074:43315", "tiger:zip_right": "43074:43315", "turn:lanes:backward": "left|through"}}, {"type": "way", "id": 487061359, "nodes": [198976035, 7919146085], "tags": {"hgv": "designated", "hgv:national_network": "yes", "highway": "primary", "lanes": "3", "lanes:backward": "1", "lanes:forward": "2", "lit": "no", "maxspeed": "45 mph", "name": "State Route 61", "old_ref:fap": "32", "ref": "SR 61", "source:hgv:national_network": "Title 23: Highways Part 658 http://ecfr.gpoaccess.gov/cgi/t/text/text-idx?c=ecfr&rgn=div5&view=text&node=23:1.0.1.7.33&idno=23", "source:old_ref:fap": "ODOT http://www.dot.state.oh.us/Divisions/Planning/TechServ/prod_services/Pages/RI06.aspx http://www.dot.state.oh.us/Divisions/ContractAdmin/Contracts/Pages/NHS-FAP.aspx", "surface": "asphalt", "tiger:cfcc": "A31", "tiger:county": "Delaware, OH:Morrow, OH", "tiger:name_base": "State Route 61", "tiger:reviewed": "yes", "tiger:zip_left": "43074:43315", "tiger:zip_right": "43074:43315", "turn:lanes:forward": "through|right"}}, {"type": "way", "id": 487061360, "nodes": [4532232138, 4532232163, 4532232148, 8080617420, 198976032, 11978057595, 198976030, 198976027], "tags": {"hgv": "designated", "hgv:national_network": "yes", "highway": "primary", "lanes": "2", "lit": "no", "maxspeed": "45 mph", "name": "State Route 61", "old_ref:fap": "32", "ref": "SR 61", "source:hgv:national_network": "Title 23: Highways Part 658 http://ecfr.gpoaccess.gov/cgi/t/text/text-idx?c=ecfr&rgn=div5&view=text&node=23:1.0.1.7.33&idno=23", "source:old_ref:fap": "ODOT http://www.dot.state.oh.us/Divisions/Planning/TechServ/prod_services/Pages/RI06.aspx http://www.dot.state.oh.us/Divisions/ContractAdmin/Contracts/Pages/NHS-FAP.aspx", "surface": "asphalt", "tiger:cfcc": "A31", "tiger:county": "Delaware, OH:Morrow, OH", "tiger:name_base": "State Route 61", "tiger:reviewed": "yes", "tiger:zip_left": "43074:43315", "tiger:zip_right": "43074:43315"}}, {"type": "way", "id": 487061378, "nodes": [4795779373, 198976066, 198976061, 4993131838, 8735332087, 4532232115, 198976050, 4532232119, 4532232126, 4532232111, 4532232122, 198967387], "tags": {"hgv": "designated", "hgv:national_network": "yes", "highway": "primary", "lanes": "2", "lit": "no", "maxspeed": "45 mph", "name": "State Route 61", "old_ref:fap": "32", "ref": "SR 61", "source:hgv:national_network": "Title 23: Highways Part 658 http://ecfr.gpoaccess.gov/cgi/t/text/text-idx?c=ecfr&rgn=div5&view=text&node=23:1.0.1.7.33&idno=23", "source:old_ref:fap": "ODOT http://www.dot.state.oh.us/Divisions/Planning/TechServ/prod_services/Pages/RI06.aspx http://www.dot.state.oh.us/Divisions/ContractAdmin/Contracts/Pages/NHS-FAP.aspx", "surface": "asphalt", "tiger:cfcc": "A31", "tiger:county": "Delaware, OH:Morrow, OH", "tiger:name_base": "State Route 61", "tiger:reviewed": "yes", "tiger:zip_left": "43074:43315", "tiger:zip_right": "43074:43315"}}, {"type": "way", "id": 647739780, "nodes": [4532230732, 4532230733, 4532230734, 4532230735, 4532230736, 4532230737, 4532230738, 4532230739, 4532230740, 4532230741, 4532230742, 4532230743, 4532230744, 4532230745, 4532230746, 4532230747, 4532232095, 4532230748, 4532230749, 4532230750], "tags": {"highway": "unclassified"}}, {"type": "way", "id": 847018285, "nodes": [4532230734, 7903747504, 7903747505, 7903747506, 7903747507, 4532230739], "tags": {"highway": "service"}}, {"type": "way", "id": 847461087, "nodes": [7908097102, 7908097103, 7908097104, 7908097105], "tags": {"highway": "service", "service": "driveway"}}, {"type": "way", "id": 847501829, "nodes": [7908443493, 7908443494, 7908443499, 7908443495, 7908443496, 7908443497, 7908443498], "tags": {"highway": "service"}}, {"type": "way", "id": 847501830, "nodes": [7908443499, 7908443509, 7908443500, 7908443501, 7908443502, 7908443503, 7908443504, 7908443505, 7908443506, 7908443507, 7908443508, 7908443509], "tags": {"access": "customers", "highway": "service"}}, {"type": "way", "id": 848282423, "nodes": [7915693364, 7915693365, 7915693366, 7915693367, 7915693368, 7915693369, 7915693370], "tags": {"highway": "service"}}, {"type": "way", "id": 848449719, "nodes": [7917091623, 7917091624, 7917091625, 7917091626, 7917091627, 7917091628, 7917091629, 7917091630, 7917091631, 7917091632, 7917091633, 7917091634], "tags": {"highway": "service", "service": "driveway"}}, {"type": "way", "id": 848449720, "nodes": [7917091635, 7917091636, 7917091637, 7917091638, 7917091639, 7917091640, 7917091641, 7917091642, 7917091643, 7917091644, 7917091645, 7917091646, 7917091647, 7917091648], "tags": {"highway": "service", "service": "driveway"}}, {"type": "way", "id": 848725962, "nodes": [7919115282, 7919146086], "tags": {"highway": "service", "oneway": "yes"}}, {"type": "way", "id": 848829195, "nodes": [7919928597, 7919928598, 7919928599, 7919928600, 7919928601, 7919928602, 7919928603, 7919928604, 7919928605, 7919928606, 7919928607, 7919928608, 7919928609, 7919928610, 7919928611], "tags": {"highway": "service", "service": "driveway"}}, {"type": "way", "id": 849690861, "nodes": [7927395280, 7927395281, 7927395282, 7927395283, 7927395284, 7927399685, 7927399686, 7927399687, 7927399688, 7927399689, 7927399690, 7927399691, 7927399692, 7927399693, 7927399694, 7927399695, 7927399696, 7927399697, 7927399698, 7927399699, 7927399700, 7927399701], "tags": {"highway": "service", "service": "driveway"}}, {"type": "way", "id": 850722786, "nodes": [7936348508, 7936348509, 7936348510, 7936348511, 7936348512, 7936348513, 7936348514, 4532232093], "tags": {"highway": "service"}}, {"type": "way", "id": 850722787, "nodes": [7936348514, 7936348515, 7936348516, 4532230750], "tags": {"highway": "service"}}, {"type": "way", "id": 850722788, "nodes": [7936348516, 7936348517, 7936348518, 7936348519], "tags": {"highway": "service"}}, {"type": "way", "id": 851029084, "nodes": [7919146086, 7919115283, 7919146087, 7919146089, 7919115284, 7919146088, 7919146085], "tags": {"highway": "service"}}, {"type": "way", "id": 851029085, "nodes": [7919146085, 4532232129, 7919115282, 4532232153, 4532232138], "tags": {"hgv": "designated", "hgv:national_network": "yes", "highway": "primary", "lanes": "3", "lanes:backward": "1", "lanes:forward": "2", "lit": "no", "maxspeed": "45 mph", "name": "State Route 61", "old_ref:fap": "32", "ref": "SR 61", "source:hgv:national_network": "Title 23: Highways Part 658 http://ecfr.gpoaccess.gov/cgi/t/text/text-idx?c=ecfr&rgn=div5&view=text&node=23:1.0.1.7.33&idno=23", "source:old_ref:fap": "ODOT http://www.dot.state.oh.us/Divisions/Planning/TechServ/prod_services/Pages/RI06.aspx http://www.dot.state.oh.us/Divisions/ContractAdmin/Contracts/Pages/NHS-FAP.aspx", "surface": "asphalt", "tiger:cfcc": "A31", "tiger:county": "Delaware, OH:Morrow, OH", "tiger:name_base": "State Route 61", "tiger:reviewed": "yes", "tiger:zip_left": "43074:43315", "tiger:zip_right": "43074:43315", "turn:lanes:forward": "|right"}}, {"type": "way", "id": 862419780, "nodes": [8034753152, 8034753153, 8034753154, 8034753155, 8034753156, 8034753157, 8034753158], "tags": {"highway": "service"}}, {"type": "way", "id": 862419781, "nodes": [8034753159, 8034753160, 8034753161], "tags": {"highway": "service"}}, {"type": "way", "id": 862419782, "nodes": [198992064, 8061875276, 8034753162, 8034753163, 8034753164, 8034753165, 8034753166, 8034753167], "tags": {"highway": "service"}}, {"type": "way", "id": 862419783, "nodes": [8034753163, 8034753168, 8034753169], "tags": {"highway": "service"}}, {"type": "way", "id": 864528392, "nodes": [7908443495, 8058009982, 8058009968, 8058009969, 8058009970, 8058009971, 8058009972, 8058009973, 8058009974, 8058009975, 8058009976, 8058009977, 8058009978, 8058009979, 8058009980, 8058009981, 8058009982], "tags": {"highway": "service"}}, {"type": "way", "id": 866910640, "nodes": [8080617420, 8080617421, 8080617422, 8080617423, 8080617424, 8080617425, 8080617426, 8080617427, 8080617428, 8080617429, 8080617430, 8080617431], "tags": {"highway": "service", "service": "driveway"}}, {"type": "way", "id": 884006615, "nodes": [4532230713, 8221336357, 8221336356], "tags": {"highway": "service"}}, {"type": "way", "id": 884006616, "nodes": [8221336357, 8221336358, 8221336359, 8221336360, 8221336361, 8221336373, 8221336362], "tags": {"highway": "service"}}, {"type": "way", "id": 884006617, "nodes": [8221336363, 8221336373, 8221336364, 8221336365], "tags": {"highway": "service"}}, {"type": "way", "id": 884006618, "nodes": [4532230713, 8221336366, 8221336367, 8221336368, 8221336369, 8221336370, 8221336371, 8221336372], "tags": {"highway": "service"}}, {"type": "way", "id": 894487776, "nodes": [7919115283, 8313982877, 8313982878, 8313982879, 8313982880], "tags": {"highway": "service"}}, {"type": "way", "id": 894508451, "nodes": [8314220785, 8314220786, 8314220791, 8314220787, 8314220788, 8314220789, 8314220790, 4532230733], "tags": {"highway": "service"}}, {"type": "way", "id": 894508452, "nodes": [8314220791, 8314220793, 8314220795, 8314220797, 8314220799, 8314220792, 4532230729], "tags": {"highway": "service"}}, {"type": "way", "id": 894508453, "nodes": [8314220793, 8314220794, 4532230732], "tags": {"highway": "service"}}, {"type": "way", "id": 894508454, "nodes": [8314220795, 8314220796, 4532230731], "tags": {"highway": "service"}}, {"type": "way", "id": 894508455, "nodes": [8314220797, 8314220798, 4532230730], "tags": {"highway": "service"}}, {"type": "way", "id": 894508456, "nodes": [8314220798, 8314220799], "tags": {"highway": "service"}}, {"type": "way", "id": 894543939, "nodes": [8314686708, 8314686709, 8314686710, 8314686711, 8314686712, 8314686713, 8314686714, 8314686715, 8314686716, 8314690917, 7936348518], "tags": {"highway": "service", "service": "alley"}}, {"type": "way", "id": 897180611, "nodes": [198991118, 8339109117, 8339109118, 7915693366], "tags": {"highway": "service"}}, {"type": "way", "id": 897408462, "nodes": [4532232108, 8340859021, 8340859022, 8340859023, 8340859024, 8340859025, 8340859026, 8340859027, 8340859028], "tags": {"highway": "service"}}, {"type": "way", "id": 975570865, "nodes": [198991136, 9027871775, 9027871776, 9027871789, 9027871777, 9027871778, 9027871779, 9027871780, 9027871781, 9027871782, 9027871783, 9027871784, 9027871785, 9027871786, 9027871787, 9027871788, 9027871789], "tags": {"highway": "service", "service": "driveway"}}, {"type": "way", "id": 993573559, "nodes": [4532230744, 4532230751, 4532230752, 4532230753, 4532230754, 4532230755, 4532230756, 4532230757, 4532230758, 4532230759, 4532230760], "tags": {"highway": "unclassified"}}, {"type": "way", "id": 994999556, "nodes": [198976027, 7917091635, 7917091623, 8584664263, 8583841015, 198976023, 6838061769, 7940648151, 198976022, 8006515675, 198967931, 7912720538, 8006515674, 8006515666, 7915525155, 198976020, 7000621036, 198967658, 6847374626, 4795306554, 8009561655, 8009561664, 6847374620, 8310781856, 229853047, 229853052, 6954112391, 6837219450, 7001207637, 7927423682, 8654335451, 229853057, 229853062, 229853068, 229853073, 8049627617, 229853078, 7231952518, 229781010, 229853081, 6953395106, 6829715452, 229853084, 6829715450, 6905275731, 6829715448, 229853087, 229800474, 6996437107, 229853091, 6829715438, 6948391640, 229853095, 7035322025, 229853099, 8021442544, 229808880, 229853105, 229853115, 229853120, 229853125, 8008881067, 229853130, 229853135, 7920355306, 8008881061, 229853139, 6755496656, 229853143, 229853147, 229853154, 7284459988, 229853160, 229853165, 6860315433, 6860315429, 229853170, 229853174, 6860315416, 229853183, 7723576028, 229853187, 229853191, 229853197, 229755521, 229853202, 229853210, 6953755004, 229853214, 229853220, 229853224, 229853229, 7912229983, 229853232, 7912229972, 229853234, 7912229965, 6863668721, 229853237, 229853239, 9188122581], "tags": {"hgv": "designated", "hgv:national_network": "yes", "highway": "primary", "lanes": "2", "lit": "no", "maxspeed": "55 mph", "name": "State Route 61", "old_ref:fap": "32", "ref": "SR 61", "source:hgv:national_network": "Title 23: Highways Part 658 http://ecfr.gpoaccess.gov/cgi/t/text/text-idx?c=ecfr&rgn=div5&view=text&node=23:1.0.1.7.33&idno=23", "source:old_ref:fap": "ODOT http://www.dot.state.oh.us/Divisions/Planning/TechServ/prod_services/Pages/RI06.aspx http://www.dot.state.oh.us/Divisions/ContractAdmin/Contracts/Pages/NHS-FAP.aspx", "surface": "asphalt", "tiger:cfcc": "A31", "tiger:county": "Delaware, OH:Morrow, OH", "tiger:name_base": "State Route 61", "tiger:reviewed": "yes", "tiger:zip_left": "43074:43315", "tiger:zip_right": "43074:43315"}}, {"type": "way", "id": 1185695439, "nodes": [11013854996, 11013877806, 11013855004, 11013877839, 11013854997, 11013854998, 11013854999, 11013855000, 11013855001, 11013855003, 11013877805, 11013855002], "tags": {"highway": "service"}}, {"type": "way", "id": 1185695440, "nodes": [11013855003, 11013877811, 11013877815, 11013877819, 11013877823, 11013877827, 11013877807, 11013855004], "tags": {"highway": "service"}}, {"type": "way", "id": 1185695441, "nodes": [11013877805, 11013877814, 11013877818, 11013877822, 11013877826, 11013877830, 11013877810, 11013877806], "tags": {"highway": "service"}}, {"type": "way", "id": 1185695442, "nodes": [11013877808, 11013877809], "tags": {"covered": "yes", "highway": "service"}}, {"type": "way", "id": 1185695443, "nodes": [11013877812, 11013877813], "tags": {"covered": "yes", "highway": "service"}}, {"type": "way", "id": 1185695444, "nodes": [11013877816, 11013877817], "tags": {"covered": "yes", "highway": "service"}}, {"type": "way", "id": 1185695445, "nodes": [11013877820, 11013877821], "tags": {"covered": "yes", "highway": "service"}}, {"type": "way", "id": 1185695446, "nodes": [11013877824, 11013877825], "tags": {"covered": "yes", "highway": "service"}}, {"type": "way", "id": 1185695447, "nodes": [11013877828, 11013877829], "tags": {"covered": "yes", "highway": "service"}}, {"type": "way", "id": 1185695448, "nodes": [11013877827, 11013877828], "tags": {"highway": "service"}}, {"type": "way", "id": 1185695449, "nodes": [11013877829, 11013877830], "tags": {"highway": "service"}}, {"type": "way", "id": 1185695450, "nodes": [11013877807, 11013877808], "tags": {"highway": "service"}}, {"type": "way", "id": 1185695451, "nodes": [11013877809, 11013877810], "tags": {"highway": "service"}}, {"type": "way", "id": 1185695452, "nodes": [11013877823, 11013877824], "tags": {"highway": "service"}}, {"type": "way", "id": 1185695453, "nodes": [11013877825, 11013877826], "tags": {"highway": "service"}}, {"type": "way", "id": 1185695454, "nodes": [11013877819, 11013877820], "tags": {"highway": "service"}}, {"type": "way", "id": 1185695455, "nodes": [11013877821, 11013877822], "tags": {"highway": "service"}}, {"type": "way", "id": 1185695456, "nodes": [11013877815, 11013877816], "tags": {"highway": "service"}}, {"type": "way", "id": 1185695457, "nodes": [11013877817, 11013877818], "tags": {"highway": "service"}}, {"type": "way", "id": 1185695458, "nodes": [11013877811, 11013877812], "tags": {"highway": "service"}}, {"type": "way", "id": 1185695459, "nodes": [11013877813, 11013877814], "tags": {"highway": "service"}}, {"type": "way", "id": 1185695460, "nodes": [11013855004, 11013877831, 11013877832, 11013877833, 11013877834, 11013877835, 11013877836, 11013877837, 11013877838, 11013877839], "tags": {"highway": "service"}}, {"type": "way", "id": 1194385393, "nodes": [11086159163, 11086159164], "tags": {"covered": "yes", "highway": "service", "service": "parking_aisle"}}, {"type": "way", "id": 1194385394, "nodes": [4532232138, 4532232139, 11086159163], "tags": {"highway": "service", "service": "parking_aisle"}}, {"type": "way", "id": 1196045181, "nodes": [11099275670, 11099275680, 11099275684, 11099275688, 11099275673, 11099275671, 11099275676, 11099275672], "tags": {"highway": "service"}}, {"type": "way", "id": 1196045182, "nodes": [11099275673, 11099275674], "tags": {"highway": "service"}}, {"type": "way", "id": 1196045183, "nodes": [11099275670, 11099275675, 11099275677, 11099275681, 11099275685, 11099275676], "tags": {"highway": "service"}}, {"type": "way", "id": 1196045184, "nodes": [11099275678, 11099275679], "tags": {"covered": "yes", "highway": "service"}}, {"type": "way", "id": 1196045185, "nodes": [11099275682, 11099275683], "tags": {"covered": "yes", "highway": "service"}}, {"type": "way", "id": 1196045186, "nodes": [11099275686, 11099275687], "tags": {"covered": "yes", "highway": "service"}}, {"type": "way", "id": 1196045187, "nodes": [11099275685, 11099275686], "tags": {"highway": "service"}}, {"type": "way", "id": 1196045188, "nodes": [11099275687, 11099275688], "tags": {"highway": "service"}}, {"type": "way", "id": 1196045189, "nodes": [11099275683, 11099275684], "tags": {"highway": "service"}}, {"type": "way", "id": 1196045190, "nodes": [11099275681, 11099275682], "tags": {"highway": "service"}}, {"type": "way", "id": 1196045191, "nodes": [11099275677, 11099275678], "tags": {"highway": "service"}}, {"type": "way", "id": 1196045192, "nodes": [11099275679, 11099275680], "tags": {"highway": "service"}}, {"type": "way", "id": 1292059871, "nodes": [11978057595, 11978057599, 11978057601, 11978057596, 11978057597, 11978057598], "tags": {"highway": "service"}}, {"type": "way", "id": 1292059872, "nodes": [11978057599, 11978057600], "tags": {"highway": "service"}}, {"type": "way", "id": 1292059873, "nodes": [11978057601, 11978057602], "tags": {"highway": "service"}}]}