[{"place_id": 25536369, "licence": "Data \u00a9 OpenStreetMap contributors, ODbL 1.0. http://osm.org/copyright", "osm_type": "way", "osm_id": 527130631, "lat": "41.177932049999995", "lon": "-85.1008454025683", "class": "tourism", "type": "hotel", "place_rank": 30, "importance": 9.99999999995449e-06, "addresstype": "tourism", "name": "Hampton Inn Dupont Road", "display_name": "Hampton Inn Dupont Road, 3520, East Dupont Road, Fort Wayne, Allen County, Indiana, 46825, United States", "boundingbox": ["41.1778094", "41.1780043", "-85.1012986", "-85.1003922"]}]