{"version": 0.6, "generator": "Overpass API 0.7.62.1 084b4234", "osm3s": {"timestamp_osm_base": "2024-07-23T20:37:26Z", "copyright": "The data included in this document is from www.openstreetmap.org. The data is made available under ODbL."}, "elements": [{"type": "node", "id": 202064652, "lat": 35.9716692, "lon": -83.2493141}, {"type": "node", "id": 202064740, "lat": 35.9703861, "lon": -83.2552206}, {"type": "node", "id": 202097854, "lat": 35.9713274, "lon": -83.2507719}, {"type": "node", "id": 202097861, "lat": 35.9715322, "lon": -83.2503758}, {"type": "node", "id": 202097866, "lat": 35.9716007, "lon": -83.24982}, {"type": "node", "id": 202097869, "lat": 35.9717374, "lon": -83.248826}, {"type": "node", "id": 202097873, "lat": 35.9717789, "lon": -83.2473498}, {"type": "node", "id": 202097890, "lat": 35.9718386, "lon": -83.2469803, "tags": {"highway": "traffic_signals", "traffic_signals": "signal"}}, {"type": "node", "id": 202097894, "lat": 35.9721257, "lon": -83.2458827}, {"type": "node", "id": 202126873, "lat": 35.9738974, "lon": -83.2474189}, {"type": "node", "id": 202126880, "lat": 35.9731098, "lon": -83.247232}, {"type": "node", "id": 202126881, "lat": 35.9728361, "lon": -83.2471905}, {"type": "node", "id": 202126882, "lat": 35.9725685, "lon": -83.2471274}, {"type": "node", "id": 202126884, "lat": 35.9722706, "lon": -83.2470715}, {"type": "node", "id": 202126886, "lat": 35.9719804, "lon": -83.2470124, "tags": {"highway": "traffic_signals", "traffic_signals": "signal"}}, {"type": "node", "id": 202127677, "lat": 35.9714706, "lon": -83.250835}, {"type": "node", "id": 202133847, "lat": 35.9711702, "lon": -83.2488513}, {"type": "node", "id": 202133849, "lat": 35.970115, "lon": -83.2505398}, {"type": "node", "id": 202172923, "lat": 35.9719912, "lon": -83.245842}, {"type": "node", "id": 1692232401, "lat": 35.9712943, "lon": -83.2519929}, {"type": "node", "id": 1910902395, "lat": 35.9717159, "lon": -83.2478619}, {"type": "node", "id": 3304440015, "lat": 35.9702039, "lon": -83.2505782}, {"type": "node", "id": 3304440019, "lat": 35.9703054, "lon": -83.2505573}, {"type": "node", "id": 3304440020, "lat": 35.970373, "lon": -83.2505103}, {"type": "node", "id": 3304440030, "lat": 35.9706047, "lon": -83.2544192}, {"type": "node", "id": 3304440037, "lat": 35.9707652, "lon": -83.2537975}, {"type": "node", "id": 3304440038, "lat": 35.97086, "lon": -83.2495498}, {"type": "node", "id": 3304440041, "lat": 35.9708584, "lon": -83.2533715}, {"type": "node", "id": 3304440047, "lat": 35.9710298, "lon": -83.252589}, {"type": "node", "id": 3304440049, "lat": 35.9710687, "lon": -83.249136}, {"type": "node", "id": 3304440051, "lat": 35.9711351, "lon": -83.2489875}, {"type": "node", "id": 3304440052, "lat": 35.9711512, "lon": -83.2519405}, {"type": "node", "id": 3304440053, "lat": 35.9712163, "lon": -83.2515439}, {"type": "node", "id": 3304440369, "lat": 35.9714093, "lon": -83.2501665}, {"type": "node", "id": 3304440379, "lat": 35.9715524, "lon": -83.2490973}, {"type": "node", "id": 3304440403, "lat": 35.9718604, "lon": -83.2479182}, {"type": "node", "id": 3304440450, "lat": 35.9722638, "lon": -83.2448713}, {"type": "node", "id": 3304440456, "lat": 35.972318, "lon": -83.2444051}, {"type": "node", "id": 3304440457, "lat": 35.9723223, "lon": -83.2440406}, {"type": "node", "id": 3304440719, "lat": 35.9733489, "lon": -83.2472895}, {"type": "node", "id": 9741861426, "lat": 35.9710449, "lon": -83.2525084}, {"type": "node", "id": 10773635745, "lat": 35.9718603, "lon": -83.2468184}, {"type": "node", "id": 10773635746, "lat": 35.9715116, "lon": -83.2466884}, {"type": "node", "id": 10773635747, "lat": 35.9713136, "lon": -83.2465835}, {"type": "node", "id": 10773635748, "lat": 35.9712655, "lon": -83.2465328}, {"type": "node", "id": 10773635749, "lat": 35.9712301, "lon": -83.2464682}, {"type": "node", "id": 10773635750, "lat": 35.9712118, "lon": -83.246407}, {"type": "node", "id": 10773635751, "lat": 35.9712132, "lon": -83.2463197}, {"type": "node", "id": 10773635752, "lat": 35.9712647, "lon": -83.2457015}, {"type": "node", "id": 10794184965, "lat": 35.971303, "lon": -83.2468698}, {"type": "node", "id": 10794184966, "lat": 35.9713021, "lon": -83.2471538}, {"type": "node", "id": 10794184967, "lat": 35.9713088, "lon": -83.2474157}, {"type": "node", "id": 10794184968, "lat": 35.9713088, "lon": -83.2476755}, {"type": "node", "id": 10794184969, "lat": 35.9713054, "lon": -83.2479831}, {"type": "node", "id": 10794184970, "lat": 35.9712735, "lon": -83.2482814}, {"type": "node", "id": 10794184971, "lat": 35.9716032, "lon": -83.2467065}, {"type": "node", "id": 10794184972, "lat": 35.9715756, "lon": -83.2469257}, {"type": "way", "id": 19435859, "nodes": [202126873, 3304440719, 202126880, 202126881, 202126882, 202126884, 202126886, 202097890], "tags": {"highway": "residential", "name": "Mariner Drive", "tiger:cfcc": "A41", "tiger:county": "Cocke, TN", "tiger:name_base": "Mariner", "tiger:name_type": "Dr"}}, {"type": "way", "id": 19436464, "nodes": [10794184970, 202133847, 3304440051, 3304440049, 3304440038, 3304440020, 3304440019, 3304440015, 202133849], "tags": {"highway": "residential", "name": "Smokey Mtn Lane", "tiger:cfcc": "A41", "tiger:county": "Cocke, TN", "tiger:name_base": "Smokey Mtn", "tiger:name_type": "Ln", "tiger:zip_left": "37821"}}, {"type": "way", "id": 323670631, "nodes": [3304440457, 3304440456, 3304440450, 202097894, 202126886, 3304440403, 202097869, 202064652, 202097866, 202097861, 202127677, 1692232401], "tags": {"highway": "primary", "lanes": "2", "oneway": "yes", "ref": "US 25W;US 70", "tiger:cfcc": "A21", "tiger:county": "Cocke, TN", "tiger:name_base": "United States Highway 25", "tiger:name_base_1": "State Highway 9:United States Highway 70", "tiger:name_base_2": "State Highway 35", "tiger:name_base_3": "State Highway 9:United States Highway 70", "tiger:zip_left": "37821", "tiger:zip_right": "37821", "unsigned_ref": "SR 9;SR 35"}}, {"type": "way", "id": 323670634, "nodes": [202064740, 3304440030, 3304440037, 3304440041, 3304440047, 9741861426, 3304440052, 3304440053, 202097854, 3304440369, 3304440379, 1910902395, 202097873, 202097890, 10773635745, 202172923], "tags": {"highway": "primary", "lanes": "2", "oneway": "yes", "ref": "US 25W;US 70", "unsigned_ref": "SR 9;SR 35"}}, {"type": "way", "id": 1158480059, "nodes": [10794184972, 10794184971, 10773635746, 10773635747, 10773635748, 10773635749, 10773635750, 10773635751, 10773635752], "tags": {"highway": "service", "service": "driveway"}}, {"type": "way", "id": 1160596400, "nodes": [202097890, 10794184972, 10794184965, 10794184966, 10794184967, 10794184968, 10794184969, 10794184970], "tags": {"highway": "residential", "name": "Smokey Mountain Lane"}}]}