[{"place_id": 6139155, "licence": "Data \u00a9 OpenStreetMap contributors, ODbL 1.0. http://osm.org/copyright", "osm_type": "way", "osm_id": 832362575, "lat": "40.67613815", "lon": "-78.23700036060535", "class": "amenity", "type": "fuel", "place_rank": 30, "importance": 9.99999999995449e-06, "addresstype": "amenity", "name": "Sheetz", "display_name": "Sheetz, 1400, Logan Avenue, Tyrone, Blair County, Pennsylvania, 16686, United States", "boundingbox": ["40.6757320", "40.6765442", "-78.2374980", "-78.2365027"]}]